{
  "auditedAt": "2026-02-25T17:07:32.353966+00:00",
  "total": 49,
  "passed": 49,
  "failed": 0,
  "results": [
    {
      "id": "qualified-health-product-designer",
      "company": "Qualified Health",
      "title": "Product Designer",
      "url": "https://job-boards.greenhouse.io/qualifiedhealth/jobs/5113771008",
      "pass": true,
      "reason": "OK",
      "status": 200,
      "checkedAt": "2026-02-27T16:30:46.477Z"
    }
  ],
  "lastRun": "2026-02-27T16:30:46.476Z",
  "summary": {
    "passed": 1,
    "failed": 0,
    "total": 1
  }
}